[{"country_id":"TUR","latitude":36.87014,"longitude":34.7655,"bright_ti4":298.41,"scan":0.37,"track":0.58,"acq_date":"2025-05-30","acq_time":16,"satellite":"N20","instrument":"VIIRS","confidence":"n","version":"2.0NRT","bright_ti5":285.38,"frp":0.77,"daynight":"N"},{"country_id":"TUR","latitude":37.25367,"longitude":30.44206,"bright_ti4":308.53,"scan":0.43,"track":0.46,"acq_date":"2025-05-30","acq_time":16,"satellite":"N20","instrument":"VIIRS","confidence":"n","version":"2.0NRT","bright_ti5":283.75,"frp":1.9,"daynight":"N"},{"country_id":"TUR","latitude":38.42645,"longitude":27.2194,"bright_ti4":308.89,"scan":0.45,"track":0.39,"acq_date":"2025-05-30","acq_time":16,"satellite":"N20","instrument":"VIIRS","confidence":"n","version":"2.0NRT","bright_ti5":289.27,"frp":1.22,"daynight":"N"},{"country_id":"TUR","latitude":38.4547,"longitude":27.26523,"bright_ti4":300.74,"scan":0.45,"track":0.39,"acq_date":"2025-05-30","acq_time":16,"satellite":"N20","instrument":"VIIRS","confidence":"n","version":"2.0NRT","bright_ti5":289.36,"frp":0.86,"daynight":"N"},{"country_id":"TUR","latitude":38.72992,"longitude":26.9324,"bright_ti4":298.56,"scan":0.43,"track":0.38,"acq_date":"2025-05-30","acq_time":16,"satellite":"N20","instrument":"VIIRS","confidence":"n","version":"2.0NRT","bright_ti5":287.21,"frp":0.72,"daynight":"N"},{"country_id":"TUR","latitude":38.7377,"longitude":26.92965,"bright_ti4":308.08,"scan":0.43,"track":0.38,"acq_date":"2025-05-30","acq_time":16,"satellite":"N20","instrument":"VIIRS","confidence":"n","version":"2.0NRT","bright_ti5":289.93,"frp":1.93,"daynight":"N"},{"country_id":"TUR","latitude":38.73842,"longitude":26.94541,"bright_ti4":312.36,"scan":0.44,"track":0.38,"acq_date":"2025-05-30","acq_time":16,"satellite":"N20","instrument":"VIIRS","confidence":"n","version":"2.0NRT","bright_ti5":291.26,"frp":1.83,"daynight":"N"},{"country_id":"TUR","latitude":38.74095,"longitude":26.95139,"bright_ti4":305.69,"scan":0.44,"track":0.38,"acq_date":"2025-05-30","acq_time":16,"satellite":"N20","instrument":"VIIRS","confidence":"n","version":"2.0NRT","bright_ti5":288.97,"frp":0.9,"daynight":"N"},{"country_id":"TUR","latitude":38.74114,"longitude":26.93069,"bright_ti4":326.98,"scan":0.43,"track":0.38,"acq_date":"2025-05-30","acq_time":16,"satellite":"N20","instrument":"VIIRS","confidence":"n","version":"2.0NRT","bright_ti5":290.12,"frp":1.93,"daynight":"N"},{"country_id":"TUR","latitude":38.74257,"longitude":26.96228,"bright_ti4":307.37,"scan":0.44,"track":0.38,"acq_date":"2025-05-30","acq_time":16,"satellite":"N20","instrument":"VIIRS","confidence":"n","version":"2.0NRT","bright_ti5":290.28,"frp":1.08,"daynight":"N"},{"country_id":"TUR","latitude":38.75146,"longitude":26.93385,"bright_ti4":312.92,"scan":0.43,"track":0.38,"acq_date":"2025-05-30","acq_time":16,"satellite":"N20","instrument":"VIIRS","confidence":"n","version":"2.0NRT","bright_ti5":287.92,"frp":1.67,"daynight":"N"},{"country_id":"TUR","latitude":39.09082,"longitude":27.51542,"bright_ti4":295.46,"scan":0.45,"track":0.39,"acq_date":"2025-05-30","acq_time":16,"satellite":"N20","instrument":"VIIRS","confidence":"n","version":"2.0NRT","bright_ti5":285.02,"frp":1.39,"daynight":"N"},{"country_id":"TUR","latitude":39.0909,"longitude":27.51099,"bright_ti4":298.32,"scan":0.45,"track":0.39,"acq_date":"2025-05-30","acq_time":16,"satellite":"N20","instrument":"VIIRS","confidence":"n","version":"2.0NRT","bright_ti5":286.08,"frp":0.89,"daynight":"N"},{"country_id":"TUR","latitude":39.16761,"longitude":27.63291,"bright_ti4":301.84,"scan":0.45,"track":0.39,"acq_date":"2025-05-30","acq_time":16,"satellite":"N20","instrument":"VIIRS","confidence":"n","version":"2.0NRT","bright_ti5":286.75,"frp":1.0,"daynight":"N"},{"country_id":"TUR","latitude":39.18207,"longitude":27.49796,"bright_ti4":298.12,"scan":0.45,"track":0.39,"acq_date":"2025-05-30","acq_time":16,"satellite":"N20","instrument":"VIIRS","confidence":"n","version":"2.0NRT","bright_ti5":285.16,"frp":0.64,"daynight":"N"},{"country_id":"TUR","latitude":39.48513,"longitude":30.03946,"bright_ti4":297.07,"scan":0.56,"track":0.43,"acq_date":"2025-05-30","acq_time":16,"satellite":"N20","instrument":"VIIRS","confidence":"n","version":"2.0NRT","bright_ti5":276.64,"frp":1.37,"daynight":"N"},{"country_id":"TUR","latitude":39.60849,"longitude":27.88178,"bright_ti4":296.98,"scan":0.46,"track":0.39,"acq_date":"2025-05-30","acq_time":16,"satellite":"N20","instrument":"VIIRS","confidence":"n","version":"2.0NRT","bright_ti5":285.05,"frp":0.31,"daynight":"N"},{"country_id":"TUR","latitude":40.44222,"longitude":27.14229,"bright_ti4":321.83,"scan":0.42,"track":0.38,"acq_date":"2025-05-30","acq_time":16,"satellite":"N20","instrument":"VIIRS","confidence":"n","version":"2.0NRT","bright_ti5":289.28,"frp":2.87,"daynight":"N"},{"country_id":"TUR","latitude":40.75753,"longitude":29.76302,"bright_ti4":299.98,"scan":0.52,"track":0.41,"acq_date":"2025-05-30","acq_time":16,"satellite":"N20","instrument":"VIIRS","confidence":"n","version":"2.0NRT","bright_ti5":287.71,"frp":1.26,"daynight":"N"},{"country_id":"TUR","latitude":40.76514,"longitude":29.53189,"bright_ti4":322.02,"scan":0.5,"track":0.41,"acq_date":"2025-05-30","acq_time":16,"satellite":"N20","instrument":"VIIRS","confidence":"n","version":"2.0NRT","bright_ti5":288.98,"frp":3.24,"daynight":"N"},{"country_id":"TUR","latitude":40.7828,"longitude":29.59984,"bright_ti4":309.01,"scan":0.51,"track":0.41,"acq_date":"2025-05-30","acq_time":16,"satellite":"N20","instrument":"VIIRS","confidence":"n","version":"2.0NRT","bright_ti5":287.07,"frp":1.06,"daynight":"N"},{"country_id":"TUR","latitude":40.78346,"longitude":29.60047,"bright_ti4":310.25,"scan":0.51,"track":0.41,"acq_date":"2025-05-30","acq_time":16,"satellite":"N20","instrument":"VIIRS","confidence":"n","version":"2.0NRT","bright_ti5":287.71,"frp":1.92,"daynight":"N"},{"country_id":"TUR","latitude":40.94785,"longitude":31.39657,"bright_ti4":295.19,"scan":0.4,"track":0.44,"acq_date":"2025-05-30","acq_time":16,"satellite":"N20","instrument":"VIIRS","confidence":"n","version":"2.0NRT","bright_ti5":281.88,"frp":0.91,"daynight":"N"},{"country_id":"TUR","latitude":41.02079,"longitude":28.55642,"bright_ti4":315.39,"scan":0.46,"track":0.39,"acq_date":"2025-05-30","acq_time":16,"satellite":"N20","instrument":"VIIRS","confidence":"n","version":"2.0NRT","bright_ti5":289.16,"frp":1.91,"daynight":"N"},{"country_id":"TUR","latitude":41.25642,"longitude":31.41566,"bright_ti4":311.43,"scan":0.4,"track":0.44,"acq_date":"2025-05-30","acq_time":16,"satellite":"N20","instrument":"VIIRS","confidence":"n","version":"2.0NRT","bright_ti5":285.13,"frp":0.96,"daynight":"N"},{"country_id":"TUR","latitude":41.25737,"longitude":31.43081,"bright_ti4":304.95,"scan":0.4,"track":0.44,"acq_date":"2025-05-30","acq_time":16,"satellite":"N20","instrument":"VIIRS","confidence":"n","version":"2.0NRT","bright_ti5":286.4,"frp":0.76,"daynight":"N"},{"country_id":"TUR","latitude":41.26228,"longitude":31.42785,"bright_ti4":297.1,"scan":0.4,"track":0.44,"acq_date":"2025-05-30","acq_time":16,"satellite":"N20","instrument":"VIIRS","confidence":"n","version":"2.0NRT","bright_ti5":286.01,"frp":1.76,"daynight":"N"},{"country_id":"TUR","latitude":41.26327,"longitude":31.42329,"bright_ti4":328.97,"scan":0.4,"track":0.44,"acq_date":"2025-05-30","acq_time":16,"satellite":"N20","instrument":"VIIRS","confidence":"n","version":"2.0NRT","bright_ti5":287.1,"frp":1.76,"daynight":"N"},{"country_id":"TUR","latitude":41.2672,"longitude":31.4248,"bright_ti4":311.22,"scan":0.4,"track":0.44,"acq_date":"2025-05-30","acq_time":16,"satellite":"N20","instrument":"VIIRS","confidence":"n","version":"2.0NRT","bright_ti5":287.13,"frp":1.76,"daynight":"N"},{"country_id":"TUR","latitude":41.63189,"longitude":27.68819,"bright_ti4":299.51,"scan":0.42,"track":0.38,"acq_date":"2025-05-30","acq_time":16,"satellite":"N20","instrument":"VIIRS","confidence":"n","version":"2.0NRT","bright_ti5":285.16,"frp":0.74,"daynight":"N"},{"country_id":"TUR","latitude":36.26168,"longitude":33.72714,"bright_ti4":300.71,"scan":0.34,"track":0.56,"acq_date":"2025-05-30","acq_time":18,"satellite":"N20","instrument":"VIIRS","confidence":"n","version":"2.0NRT","bright_ti5":284.46,"frp":0.97,"daynight":"N"},{"country_id":"TUR","latitude":36.26284,"longitude":33.73143,"bright_ti4":301.41,"scan":0.34,"track":0.56,"acq_date":"2025-05-30","acq_time":18,"satellite":"N20","instrument":"VIIRS","confidence":"n","version":"2.0NRT","bright_ti5":287.7,"frp":0.92,"daynight":"N"},{"country_id":"TUR","latitude":36.26378,"longitude":33.72766,"bright_ti4":297.98,"scan":0.34,"track":0.56,"acq_date":"2025-05-30","acq_time":18,"satellite":"N20","instrument":"VIIRS","confidence":"n","version":"2.0NRT","bright_ti5":284.05,"frp":0.76,"daynight":"N"}]