[{"country_id":"TUR","latitude":41.26167,"longitude":31.4264,"bright_ti4":306.57,"scan":0.49,"track":0.65,"acq_date":"2025-03-12","acq_time":48,"satellite":"N21","instrument":"VIIRS","confidence":"n","version":"2.0NRT","bright_ti5":284.62,"frp":3.02,"daynight":"N"},{"country_id":"TUR","latitude":41.26329,"longitude":31.42102,"bright_ti4":301.16,"scan":0.49,"track":0.65,"acq_date":"2025-03-12","acq_time":48,"satellite":"N21","instrument":"VIIRS","confidence":"n","version":"2.0NRT","bright_ti5":283.49,"frp":1.96,"daynight":"N"},{"country_id":"TUR","latitude":37.25006,"longitude":30.44092,"bright_ti4":298.69,"scan":0.58,"track":0.69,"acq_date":"2025-03-12","acq_time":50,"satellite":"N21","instrument":"VIIRS","confidence":"n","version":"2.0NRT","bright_ti5":276.07,"frp":1.3,"daynight":"N"},{"country_id":"TUR","latitude":41.25442,"longitude":31.41403,"bright_ti4":295.82,"scan":0.49,"track":0.65,"acq_date":"2025-03-12","acq_time":50,"satellite":"N21","instrument":"VIIRS","confidence":"n","version":"2.0NRT","bright_ti5":279.9,"frp":0.68,"daynight":"N"},{"country_id":"TUR","latitude":41.25676,"longitude":31.42797,"bright_ti4":297.98,"scan":0.49,"track":0.65,"acq_date":"2025-03-12","acq_time":50,"satellite":"N21","instrument":"VIIRS","confidence":"n","version":"2.0NRT","bright_ti5":281.63,"frp":0.73,"daynight":"N"},{"country_id":"TUR","latitude":41.26394,"longitude":31.42556,"bright_ti4":311.96,"scan":0.49,"track":0.65,"acq_date":"2025-03-12","acq_time":50,"satellite":"N21","instrument":"VIIRS","confidence":"n","version":"2.0NRT","bright_ti5":286.2,"frp":2.87,"daynight":"N"},{"country_id":"TUR","latitude":39.93908,"longitude":44.32485,"bright_ti4":328.72,"scan":0.66,"track":0.73,"acq_date":"2025-03-12","acq_time":850,"satellite":"N21","instrument":"VIIRS","confidence":"n","version":"2.0NRT","bright_ti5":297.68,"frp":4.49,"daynight":"D"},{"country_id":"TUR","latitude":39.98853,"longitude":44.27422,"bright_ti4":335.64,"scan":0.67,"track":0.73,"acq_date":"2025-03-12","acq_time":850,"satellite":"N21","instrument":"VIIRS","confidence":"n","version":"2.0NRT","bright_ti5":298.4,"frp":4.25,"daynight":"D"},{"country_id":"TUR","latitude":36.26418,"longitude":33.73206,"bright_ti4":327.37,"scan":0.45,"track":0.39,"acq_date":"2025-03-12","acq_time":1030,"satellite":"N21","instrument":"VIIRS","confidence":"l","version":"2.0NRT","bright_ti5":300.79,"frp":4.67,"daynight":"D"},{"country_id":"TUR","latitude":36.73004,"longitude":36.21167,"bright_ti4":333.6,"scan":0.39,"track":0.36,"acq_date":"2025-03-12","acq_time":1030,"satellite":"N21","instrument":"VIIRS","confidence":"l","version":"2.0NRT","bright_ti5":304.68,"frp":5.22,"daynight":"D"},{"country_id":"TUR","latitude":36.80064,"longitude":34.96472,"bright_ti4":331.88,"scan":0.41,"track":0.37,"acq_date":"2025-03-12","acq_time":1030,"satellite":"N21","instrument":"VIIRS","confidence":"n","version":"2.0NRT","bright_ti5":304.7,"frp":1.57,"daynight":"D"},{"country_id":"TUR","latitude":36.86613,"longitude":34.70755,"bright_ti4":333.53,"scan":0.41,"track":0.37,"acq_date":"2025-03-12","acq_time":1030,"satellite":"N21","instrument":"VIIRS","confidence":"n","version":"2.0NRT","bright_ti5":302.31,"frp":3.38,"daynight":"D"},{"country_id":"TUR","latitude":36.93182,"longitude":37.90395,"bright_ti4":335.6,"scan":0.39,"track":0.36,"acq_date":"2025-03-12","acq_time":1030,"satellite":"N21","instrument":"VIIRS","confidence":"n","version":"2.0NRT","bright_ti5":308.38,"frp":5.43,"daynight":"D"},{"country_id":"TUR","latitude":37.34644,"longitude":37.02817,"bright_ti4":338.03,"scan":0.38,"track":0.36,"acq_date":"2025-03-12","acq_time":1030,"satellite":"N21","instrument":"VIIRS","confidence":"l","version":"2.0NRT","bright_ti5":310.8,"frp":7.31,"daynight":"D"},{"country_id":"TUR","latitude":37.55354,"longitude":36.86544,"bright_ti4":331.73,"scan":0.38,"track":0.36,"acq_date":"2025-03-12","acq_time":1030,"satellite":"N21","instrument":"VIIRS","confidence":"n","version":"2.0NRT","bright_ti5":299.94,"frp":4.03,"daynight":"D"},{"country_id":"TUR","latitude":37.76818,"longitude":31.64532,"bright_ti4":335.46,"scan":0.52,"track":0.41,"acq_date":"2025-03-12","acq_time":1030,"satellite":"N21","instrument":"VIIRS","confidence":"n","version":"2.0NRT","bright_ti5":304.32,"frp":67.49,"daynight":"D"},{"country_id":"TUR","latitude":37.78897,"longitude":31.0043,"bright_ti4":332.76,"scan":0.55,"track":0.43,"acq_date":"2025-03-12","acq_time":1030,"satellite":"N21","instrument":"VIIRS","confidence":"n","version":"2.0NRT","bright_ti5":301.75,"frp":6.83,"daynight":"D"},{"country_id":"TUR","latitude":38.10279,"longitude":41.20022,"bright_ti4":332.23,"scan":0.48,"track":0.4,"acq_date":"2025-03-12","acq_time":1030,"satellite":"N21","instrument":"VIIRS","confidence":"l","version":"2.0NRT","bright_ti5":304.93,"frp":2.13,"daynight":"D"},{"country_id":"TUR","latitude":38.21183,"longitude":35.05895,"bright_ti4":330.48,"scan":0.4,"track":0.37,"acq_date":"2025-03-12","acq_time":1030,"satellite":"N21","instrument":"VIIRS","confidence":"l","version":"2.0NRT","bright_ti5":303.17,"frp":1.08,"daynight":"D"},{"country_id":"TUR","latitude":38.28492,"longitude":37.98591,"bright_ti4":340.11,"scan":0.39,"track":0.36,"acq_date":"2025-03-12","acq_time":1030,"satellite":"N21","instrument":"VIIRS","confidence":"n","version":"2.0NRT","bright_ti5":304.06,"frp":3.83,"daynight":"D"},{"country_id":"TUR","latitude":38.36662,"longitude":38.10527,"bright_ti4":332.48,"scan":0.39,"track":0.37,"acq_date":"2025-03-12","acq_time":1030,"satellite":"N21","instrument":"VIIRS","confidence":"n","version":"2.0NRT","bright_ti5":302.41,"frp":1.91,"daynight":"D"},{"country_id":"TUR","latitude":38.39886,"longitude":34.6279,"bright_ti4":352.33,"scan":0.4,"track":0.37,"acq_date":"2025-03-12","acq_time":1030,"satellite":"N21","instrument":"VIIRS","confidence":"n","version":"2.0NRT","bright_ti5":298.22,"frp":9.23,"daynight":"D"},{"country_id":"TUR","latitude":38.40805,"longitude":34.62062,"bright_ti4":335.47,"scan":0.4,"track":0.37,"acq_date":"2025-03-12","acq_time":1030,"satellite":"N21","instrument":"VIIRS","confidence":"n","version":"2.0NRT","bright_ti5":300.92,"frp":3.78,"daynight":"D"},{"country_id":"TUR","latitude":38.67245,"longitude":39.85484,"bright_ti4":333.93,"scan":0.44,"track":0.38,"acq_date":"2025-03-12","acq_time":1030,"satellite":"N21","instrument":"VIIRS","confidence":"n","version":"2.0NRT","bright_ti5":306.99,"frp":2.7,"daynight":"D"},{"country_id":"TUR","latitude":38.94158,"longitude":40.04825,"bright_ti4":332.12,"scan":0.45,"track":0.39,"acq_date":"2025-03-12","acq_time":1030,"satellite":"N21","instrument":"VIIRS","confidence":"n","version":"2.0NRT","bright_ti5":306.2,"frp":7.29,"daynight":"D"},{"country_id":"TUR","latitude":38.07784,"longitude":30.85146,"bright_ti4":334.1,"scan":0.56,"track":0.43,"acq_date":"2025-03-12","acq_time":1032,"satellite":"N21","instrument":"VIIRS","confidence":"n","version":"2.0NRT","bright_ti5":298.29,"frp":6.13,"daynight":"D"},{"country_id":"TUR","latitude":38.22241,"longitude":29.79469,"bright_ti4":335.96,"scan":0.41,"track":0.45,"acq_date":"2025-03-12","acq_time":1032,"satellite":"N21","instrument":"VIIRS","confidence":"n","version":"2.0NRT","bright_ti5":302.54,"frp":4.33,"daynight":"D"},{"country_id":"TUR","latitude":38.27689,"longitude":29.88913,"bright_ti4":329.44,"scan":0.41,"track":0.45,"acq_date":"2025-03-12","acq_time":1032,"satellite":"N21","instrument":"VIIRS","confidence":"n","version":"2.0NRT","bright_ti5":294.2,"frp":1.39,"daynight":"D"},{"country_id":"TUR","latitude":38.2864,"longitude":31.96687,"bright_ti4":336.73,"scan":0.49,"track":0.4,"acq_date":"2025-03-12","acq_time":1032,"satellite":"N21","instrument":"VIIRS","confidence":"n","version":"2.0NRT","bright_ti5":296.31,"frp":11.45,"daynight":"D"},{"country_id":"TUR","latitude":38.29092,"longitude":29.85536,"bright_ti4":340.95,"scan":0.41,"track":0.45,"acq_date":"2025-03-12","acq_time":1032,"satellite":"N21","instrument":"VIIRS","confidence":"n","version":"2.0NRT","bright_ti5":295.14,"frp":18.63,"daynight":"D"},{"country_id":"TUR","latitude":38.29393,"longitude":29.8495,"bright_ti4":340.1,"scan":0.41,"track":0.45,"acq_date":"2025-03-12","acq_time":1032,"satellite":"N21","instrument":"VIIRS","confidence":"n","version":"2.0NRT","bright_ti5":294.9,"frp":3.97,"daynight":"D"},{"country_id":"TUR","latitude":38.51561,"longitude":32.36481,"bright_ti4":336.22,"scan":0.47,"track":0.4,"acq_date":"2025-03-12","acq_time":1032,"satellite":"N21","instrument":"VIIRS","confidence":"n","version":"2.0NRT","bright_ti5":289.98,"frp":5.8,"daynight":"D"},{"country_id":"TUR","latitude":38.74161,"longitude":35.13196,"bright_ti4":345.64,"scan":0.39,"track":0.36,"acq_date":"2025-03-12","acq_time":1032,"satellite":"N21","instrument":"VIIRS","confidence":"n","version":"2.0NRT","bright_ti5":299.86,"frp":5.97,"daynight":"D"},{"country_id":"TUR","latitude":39.35176,"longitude":31.97602,"bright_ti4":334.17,"scan":0.47,"track":0.4,"acq_date":"2025-03-12","acq_time":1032,"satellite":"N21","instrument":"VIIRS","confidence":"n","version":"2.0NRT","bright_ti5":290.6,"frp":7.7,"daynight":"D"},{"country_id":"TUR","latitude":39.35232,"longitude":31.97329,"bright_ti4":339.31,"scan":0.47,"track":0.4,"acq_date":"2025-03-12","acq_time":1032,"satellite":"N21","instrument":"VIIRS","confidence":"n","version":"2.0NRT","bright_ti5":289.03,"frp":8.64,"daynight":"D"},{"country_id":"TUR","latitude":39.54902,"longitude":35.08201,"bright_ti4":327.77,"scan":0.39,"track":0.36,"acq_date":"2025-03-12","acq_time":1032,"satellite":"N21","instrument":"VIIRS","confidence":"n","version":"2.0NRT","bright_ti5":294.98,"frp":1.89,"daynight":"D"},{"country_id":"TUR","latitude":39.64335,"longitude":31.78198,"bright_ti4":334.27,"scan":0.48,"track":0.4,"acq_date":"2025-03-12","acq_time":1032,"satellite":"N21","instrument":"VIIRS","confidence":"n","version":"2.0NRT","bright_ti5":300.48,"frp":3.69,"daynight":"D"},{"country_id":"TUR","latitude":39.77832,"longitude":37.31018,"bright_ti4":334.12,"scan":0.39,"track":0.36,"acq_date":"2025-03-12","acq_time":1032,"satellite":"N21","instrument":"VIIRS","confidence":"n","version":"2.0NRT","bright_ti5":299.03,"frp":6.7,"daynight":"D"},{"country_id":"TUR","latitude":39.99264,"longitude":43.99855,"bright_ti4":338.87,"scan":0.46,"track":0.47,"acq_date":"2025-03-12","acq_time":1032,"satellite":"N21","instrument":"VIIRS","confidence":"n","version":"2.0NRT","bright_ti5":306.85,"frp":4.24,"daynight":"D"},{"country_id":"TUR","latitude":40.0134,"longitude":35.97979,"bright_ti4":325.95,"scan":0.38,"track":0.36,"acq_date":"2025-03-12","acq_time":1032,"satellite":"N21","instrument":"VIIRS","confidence":"n","version":"2.0NRT","bright_ti5":290.8,"frp":1.75,"daynight":"D"},{"country_id":"TUR","latitude":40.34809,"longitude":33.49811,"bright_ti4":325.53,"scan":0.41,"track":0.37,"acq_date":"2025-03-12","acq_time":1032,"satellite":"N21","instrument":"VIIRS","confidence":"n","version":"2.0NRT","bright_ti5":290.43,"frp":1.68,"daynight":"D"},{"country_id":"TUR","latitude":41.01978,"longitude":34.62233,"bright_ti4":329.45,"scan":0.39,"track":0.36,"acq_date":"2025-03-12","acq_time":1032,"satellite":"N21","instrument":"VIIRS","confidence":"n","version":"2.0NRT","bright_ti5":283.33,"frp":1.9,"daynight":"D"},{"country_id":"TUR","latitude":41.04012,"longitude":34.2254,"bright_ti4":346.48,"scan":0.39,"track":0.37,"acq_date":"2025-03-12","acq_time":1032,"satellite":"N21","instrument":"VIIRS","confidence":"n","version":"2.0NRT","bright_ti5":295.81,"frp":7.41,"daynight":"D"},{"country_id":"TUR","latitude":41.64718,"longitude":36.00827,"bright_ti4":333.46,"scan":0.38,"track":0.36,"acq_date":"2025-03-12","acq_time":1032,"satellite":"N21","instrument":"VIIRS","confidence":"n","version":"2.0NRT","bright_ti5":288.5,"frp":3.11,"daynight":"D"}]